bandparams.py
bandparams-0.1.data/data/share/doc/bandparams/LICENSE
bandparams-0.1.data/data/share/doc/bandparams/README.rst
bandparams-0.1.dist-info/LICENSE
bandparams-0.1.dist-info/METADATA
bandparams-0.1.dist-info/WHEEL
bandparams-0.1.dist-info/entry_points.txt
bandparams-0.1.dist-info/top_level.txt
bandparams-0.1.dist-info/RECORD
