Metadata-Version: 2.1
Name: bandparams
Version: 0.1
Summary: Calculate band parameters, such as max, barycenter, width
Author: Mariusz Radon
Author-email: mariusz.radon@uj.edu.pl
Requires-Python: >=3.6
License-File: LICENSE
Requires-Dist: numpy
Requires-Dist: pandas
